<?xml version="1.0"?>
<testResults>
  <FitNesseVersion>v20151230</FitNesseVersion>
  <rootPath>HotelSearchDetails.Search</rootPath>
    <result>
    <counts>
      <right>19</right>
      <wrong>1</wrong>
      <ignores>0</ignores>
      <exceptions>26</exceptions>
    </counts>
    <date>2016-04-21T11:25:30+01:00</date>
    <runTimeInMillis>163</runTimeInMillis>
    <content>&lt;br/&gt;&lt;h1&gt;Display Hotel List&lt;/h1&gt;
&lt;h4&gt;Test: Given a set of hotels all hotels will be displayed in the correct order&lt;/h4&gt;
&lt;table&gt;
	&lt;tr&gt;
		&lt;td&gt;&lt;span class="pass"&gt;FIT Hotel Data Set&lt;/span&gt;&lt;/td&gt;
		&lt;td colspan="3"&gt;fakeData1&lt;/td&gt;
	&lt;/tr&gt;
	&lt;tr&gt;
		&lt;td&gt;title&lt;/td&gt;
		&lt;td&gt;star rating&lt;/td&gt;
		&lt;td&gt;image url&lt;/td&gt;
		&lt;td&gt;id&lt;/td&gt;
	&lt;/tr&gt;
	&lt;tr&gt;
		&lt;td&gt;hotel1&lt;/td&gt;
		&lt;td&gt;1&lt;/td&gt;
		&lt;td&gt;http://hotel1.com&lt;/td&gt;
		&lt;td&gt;1&lt;/td&gt;
	&lt;/tr&gt;
	&lt;tr&gt;
		&lt;td&gt;hotel2&lt;/td&gt;
		&lt;td&gt;2.5&lt;/td&gt;
		&lt;td&gt;http://hotel2.com&lt;/td&gt;
		&lt;td&gt;4&lt;/td&gt;
	&lt;/tr&gt;
	&lt;tr&gt;
		&lt;td&gt;hotel3&lt;/td&gt;
		&lt;td&gt;5&lt;/td&gt;
		&lt;td&gt;http://hotel3.com&lt;/td&gt;
		&lt;td&gt;3&lt;/td&gt;
	&lt;/tr&gt;
&lt;/table&gt;
&lt;br/&gt;&lt;br/&gt;&lt;br/&gt;&lt;br/&gt;&lt;table&gt;
	&lt;tr class="slimRowTitle"&gt;
		&lt;td&gt;&lt;span class="pass"&gt;Ordered Query:FIT Presented Hotels&lt;/span&gt;&lt;/td&gt;
		&lt;td colspan="3"&gt;fakeData1&lt;/td&gt;
	&lt;/tr&gt;
	&lt;tr class="slimRowTitle"&gt;
		&lt;td&gt;title&lt;/td&gt;
		&lt;td&gt;star rating&lt;/td&gt;
		&lt;td&gt;image url&lt;/td&gt;
		&lt;td&gt;id&lt;/td&gt;
	&lt;/tr&gt;
	&lt;tr class="slimRowColor1"&gt;
		&lt;td&gt;&lt;span class="pass"&gt;hotel1&lt;/span&gt;&lt;/td&gt;
		&lt;td&gt;&lt;span class="pass"&gt;1&lt;/span&gt;&lt;/td&gt;
		&lt;td&gt;&lt;span class="pass"&gt;http://hotel1.com&lt;/span&gt;&lt;/td&gt;
		&lt;td&gt;&lt;span class="pass"&gt;1&lt;/span&gt;&lt;/td&gt;
	&lt;/tr&gt;
	&lt;tr class="slimRowColor0"&gt;
		&lt;td&gt;&lt;span class="pass"&gt;hotel2&lt;/span&gt;&lt;/td&gt;
		&lt;td&gt;&lt;span class="pass"&gt;2.5&lt;/span&gt;&lt;/td&gt;
		&lt;td&gt;&lt;span class="pass"&gt;http://hotel2.com&lt;/span&gt;&lt;/td&gt;
		&lt;td&gt;[&lt;span class="diff"&gt;4&lt;/span&gt;] &lt;span class="fail"&gt;expected [&lt;/span&gt;&lt;span class="diff"&gt;2&lt;/span&gt;&lt;span class="fail"&gt;]&lt;/span&gt;&lt;/td&gt;
	&lt;/tr&gt;
	&lt;tr class="slimRowColor1"&gt;
		&lt;td&gt;&lt;span class="pass"&gt;hotel3&lt;/span&gt;&lt;/td&gt;
		&lt;td&gt;&lt;span class="pass"&gt;5&lt;/span&gt;&lt;/td&gt;
		&lt;td&gt;&lt;span class="pass"&gt;http://hotel3.com&lt;/span&gt;&lt;/td&gt;
		&lt;td&gt;&lt;span class="pass"&gt;3&lt;/span&gt;&lt;/td&gt;
	&lt;/tr&gt;
&lt;/table&gt;
&lt;br/&gt;&lt;h4&gt;Test: Given a set of no hotels display an empty list&lt;/h4&gt;
&lt;h4&gt;Test: Given a hotel without an id, do not display hotel but display all others&lt;/h4&gt;
&lt;table&gt;
	&lt;tr&gt;
		&lt;td&gt;&lt;span class="pass"&gt;FIT Hotel Data Set&lt;/span&gt;&lt;/td&gt;
		&lt;td colspan="3"&gt;fakeData3&lt;/td&gt;
	&lt;/tr&gt;
	&lt;tr&gt;
		&lt;td&gt;title&lt;/td&gt;
		&lt;td&gt;star rating&lt;/td&gt;
		&lt;td&gt;image url&lt;/td&gt;
		&lt;td&gt;id&lt;/td&gt;
	&lt;/tr&gt;
	&lt;tr&gt;
		&lt;td&gt;hotel1&lt;/td&gt;
		&lt;td&gt;1&lt;/td&gt;
		&lt;td&gt;http://hotel1.com&lt;/td&gt;
		&lt;td&gt;1&lt;/td&gt;
	&lt;/tr&gt;
	&lt;tr&gt;
		&lt;td&gt;hotel2&lt;/td&gt;
		&lt;td&gt;2.5&lt;/td&gt;
		&lt;td&gt;http://hotel2.com&lt;/td&gt;
		&lt;td&gt;&lt;/td&gt;
	&lt;/tr&gt;
	&lt;tr&gt;
		&lt;td&gt;hotel3&lt;/td&gt;
		&lt;td&gt;5&lt;/td&gt;
		&lt;td&gt;http://hotel3.com&lt;/td&gt;
		&lt;td&gt;3&lt;/td&gt;
	&lt;/tr&gt;
&lt;/table&gt;
&lt;br/&gt;&lt;table&gt;
	&lt;tr class="slimRowTitle"&gt;
		&lt;td&gt;&lt;span class="pass"&gt;Ordered Query:FIT Presented Hotels&lt;/span&gt;&lt;/td&gt;
		&lt;td colspan="3"&gt;fakeData3&lt;/td&gt;
	&lt;/tr&gt;
	&lt;tr class="slimRowTitle"&gt;
		&lt;td&gt;title&lt;/td&gt;
		&lt;td&gt;star rating&lt;/td&gt;
		&lt;td&gt;image url&lt;/td&gt;
		&lt;td&gt;id&lt;/td&gt;
	&lt;/tr&gt;
	&lt;tr class="slimRowColor1"&gt;
		&lt;td&gt;&lt;span class="pass"&gt;hotel1&lt;/span&gt;&lt;/td&gt;
		&lt;td&gt;&lt;span class="pass"&gt;1&lt;/span&gt;&lt;/td&gt;
		&lt;td&gt;&lt;span class="pass"&gt;http://hotel1.com&lt;/span&gt;&lt;/td&gt;
		&lt;td&gt;&lt;span class="pass"&gt;1&lt;/span&gt;&lt;/td&gt;
	&lt;/tr&gt;
	&lt;tr class="slimRowColor0"&gt;
		&lt;td&gt;&lt;span class="pass"&gt;hotel3&lt;/span&gt;&lt;/td&gt;
		&lt;td&gt;&lt;span class="pass"&gt;5&lt;/span&gt;&lt;/td&gt;
		&lt;td&gt;&lt;span class="pass"&gt;http://hotel3.com&lt;/span&gt;&lt;/td&gt;
		&lt;td&gt;&lt;span class="pass"&gt;3&lt;/span&gt;&lt;/td&gt;
	&lt;/tr&gt;
&lt;/table&gt;
&lt;br/&gt;&lt;h4&gt;Test: Given a set of error cases, display correct text to user&lt;/h4&gt;
&lt;table&gt;
	&lt;tr&gt;
		&lt;td colspan="3"&gt;FIT Presented Error &lt;span class="error"&gt;Could not find class FITPresentedError.&lt;/span&gt;&lt;/td&gt;
	&lt;/tr&gt;
	&lt;tr&gt;
		&lt;td&gt;error&lt;/td&gt;
		&lt;td&gt;http status&lt;/td&gt;
		&lt;td&gt;displayed text?&lt;/td&gt;
	&lt;/tr&gt;
	&lt;tr&gt;
		&lt;td&gt;no error &lt;span class="error"&gt;The instance decisionTable_4. does not exist&lt;/span&gt;&lt;/td&gt;
		&lt;td&gt; &lt;span class="error"&gt;The instance decisionTable_4. does not exist&lt;/span&gt;&lt;/td&gt;
		&lt;td&gt; &lt;span class="error"&gt;The instance decisionTable_4. does not exist&lt;/span&gt;&lt;/td&gt;
	&lt;/tr&gt;
	&lt;tr&gt;
		&lt;td&gt;http error &lt;span class="error"&gt;The instance decisionTable_4. does not exist&lt;/span&gt;&lt;/td&gt;
		&lt;td&gt;400 &lt;span class="error"&gt;The instance decisionTable_4. does not exist&lt;/span&gt;&lt;/td&gt;
		&lt;td&gt;Network error please try again &lt;span class="error"&gt;The instance decisionTable_4. does not exist&lt;/span&gt;&lt;/td&gt;
	&lt;/tr&gt;
	&lt;tr&gt;
		&lt;td&gt;time out &lt;span class="error"&gt;The instance decisionTable_4. does not exist&lt;/span&gt;&lt;/td&gt;
		&lt;td&gt; &lt;span class="error"&gt;The instance decisionTable_4. does not exist&lt;/span&gt;&lt;/td&gt;
		&lt;td&gt;Time out please try again &lt;span class="error"&gt;The instance decisionTable_4. does not exist&lt;/span&gt;&lt;/td&gt;
	&lt;/tr&gt;
	&lt;tr&gt;
		&lt;td&gt;data invalid &lt;span class="error"&gt;The instance decisionTable_4. does not exist&lt;/span&gt;&lt;/td&gt;
		&lt;td&gt; &lt;span class="error"&gt;The instance decisionTable_4. does not exist&lt;/span&gt;&lt;/td&gt;
		&lt;td&gt;Data invalid please try again &lt;span class="error"&gt;The instance decisionTable_4. does not exist&lt;/span&gt;&lt;/td&gt;
	&lt;/tr&gt;
&lt;/table&gt;
&lt;br/&gt;&lt;h4&gt;Test: Given the user selects a hotel at an index the correct hotel is request to show more details&lt;/h4&gt;
&lt;table&gt;
	&lt;tr class="slimRowTitle"&gt;
		&lt;td colspan="4"&gt;script: Presented Details &lt;span class="error"&gt;Could not find class PresentedDetails.&lt;/span&gt;&lt;/td&gt;
	&lt;/tr&gt;
	&lt;tr class="slimRowColor6"&gt;
		&lt;td&gt;select row &lt;span class="error"&gt;The instance scriptTableActor. does not exist&lt;/span&gt;&lt;/td&gt;
		&lt;td&gt;1&lt;/td&gt;
		&lt;td&gt;showing details&lt;/td&gt;
		&lt;td&gt;hotel 2&lt;/td&gt;
	&lt;/tr&gt;
&lt;/table&gt;
</content>
    <relativePageName>Search</relativePageName>
            <instructions>
            <instructionResult>
        <instruction>{id='decisionTable_0_0', instruction='make', instanceName='decisionTable_0', className='FITHotelDataSet', args=[fakeData1]}</instruction>
        <slimResult>pass(FIT Hotel Data Set)</slimResult>
                <expectation>
                    <status>pass</status>
                    <instructionId>decisionTable_0_0</instructionId>
                    <col>0</col>
                              <row>0</row>
                    <type>ConstructionExpectation</type>
                                        <evaluationMessage>FIT Hotel Data Set</evaluationMessage>
                  </expectation>
              </instructionResult>
            <instructionResult>
        <instruction>{id='decisionTable_0_4', instruction='call', instanceName='decisionTable_0', methodName='setTitle', args=[hotel1]}</instruction>
        <slimResult></slimResult>
                <expectation>
                    <instructionId>decisionTable_0_4</instructionId>
                    <col>0</col>
                              <row>2</row>
                    <type>VoidReturnExpectation</type>
                                      </expectation>
              </instructionResult>
            <instructionResult>
        <instruction>{id='decisionTable_0_5', instruction='call', instanceName='decisionTable_0', methodName='setStarRating', args=[1]}</instruction>
        <slimResult></slimResult>
                <expectation>
                    <instructionId>decisionTable_0_5</instructionId>
                    <col>1</col>
                              <row>2</row>
                    <type>VoidReturnExpectation</type>
                                      </expectation>
              </instructionResult>
            <instructionResult>
        <instruction>{id='decisionTable_0_6', instruction='call', instanceName='decisionTable_0', methodName='setImageUrl', args=[http://hotel1.com]}</instruction>
        <slimResult></slimResult>
                <expectation>
                    <instructionId>decisionTable_0_6</instructionId>
                    <col>2</col>
                              <row>2</row>
                    <type>VoidReturnExpectation</type>
                                      </expectation>
              </instructionResult>
            <instructionResult>
        <instruction>{id='decisionTable_0_7', instruction='call', instanceName='decisionTable_0', methodName='setId', args=[1]}</instruction>
        <slimResult></slimResult>
                <expectation>
                    <instructionId>decisionTable_0_7</instructionId>
                    <col>3</col>
                              <row>2</row>
                    <type>VoidReturnExpectation</type>
                                      </expectation>
              </instructionResult>
            <instructionResult>
        <instruction>{id='decisionTable_0_10', instruction='call', instanceName='decisionTable_0', methodName='setTitle', args=[hotel2]}</instruction>
        <slimResult></slimResult>
                <expectation>
                    <instructionId>decisionTable_0_10</instructionId>
                    <col>0</col>
                              <row>3</row>
                    <type>VoidReturnExpectation</type>
                                      </expectation>
              </instructionResult>
            <instructionResult>
        <instruction>{id='decisionTable_0_11', instruction='call', instanceName='decisionTable_0', methodName='setStarRating', args=[2.5]}</instruction>
        <slimResult></slimResult>
                <expectation>
                    <instructionId>decisionTable_0_11</instructionId>
                    <col>1</col>
                              <row>3</row>
                    <type>VoidReturnExpectation</type>
                                      </expectation>
              </instructionResult>
            <instructionResult>
        <instruction>{id='decisionTable_0_12', instruction='call', instanceName='decisionTable_0', methodName='setImageUrl', args=[http://hotel2.com]}</instruction>
        <slimResult></slimResult>
                <expectation>
                    <instructionId>decisionTable_0_12</instructionId>
                    <col>2</col>
                              <row>3</row>
                    <type>VoidReturnExpectation</type>
                                      </expectation>
              </instructionResult>
            <instructionResult>
        <instruction>{id='decisionTable_0_13', instruction='call', instanceName='decisionTable_0', methodName='setId', args=[4]}</instruction>
        <slimResult></slimResult>
                <expectation>
                    <instructionId>decisionTable_0_13</instructionId>
                    <col>3</col>
                              <row>3</row>
                    <type>VoidReturnExpectation</type>
                                      </expectation>
              </instructionResult>
            <instructionResult>
        <instruction>{id='decisionTable_0_16', instruction='call', instanceName='decisionTable_0', methodName='setTitle', args=[hotel3]}</instruction>
        <slimResult></slimResult>
                <expectation>
                    <instructionId>decisionTable_0_16</instructionId>
                    <col>0</col>
                              <row>4</row>
                    <type>VoidReturnExpectation</type>
                                      </expectation>
              </instructionResult>
            <instructionResult>
        <instruction>{id='decisionTable_0_17', instruction='call', instanceName='decisionTable_0', methodName='setStarRating', args=[5]}</instruction>
        <slimResult></slimResult>
                <expectation>
                    <instructionId>decisionTable_0_17</instructionId>
                    <col>1</col>
                              <row>4</row>
                    <type>VoidReturnExpectation</type>
                                      </expectation>
              </instructionResult>
            <instructionResult>
        <instruction>{id='decisionTable_0_18', instruction='call', instanceName='decisionTable_0', methodName='setImageUrl', args=[http://hotel3.com]}</instruction>
        <slimResult></slimResult>
                <expectation>
                    <instructionId>decisionTable_0_18</instructionId>
                    <col>2</col>
                              <row>4</row>
                    <type>VoidReturnExpectation</type>
                                      </expectation>
              </instructionResult>
            <instructionResult>
        <instruction>{id='decisionTable_0_19', instruction='call', instanceName='decisionTable_0', methodName='setId', args=[3]}</instruction>
        <slimResult></slimResult>
                <expectation>
                    <instructionId>decisionTable_0_19</instructionId>
                    <col>3</col>
                              <row>4</row>
                    <type>VoidReturnExpectation</type>
                                      </expectation>
              </instructionResult>
            <instructionResult>
        <instruction>{id='queryTable_1_0', instruction='make', instanceName='queryTable_1', className='FITPresentedHotels', args=[fakeData1]}</instruction>
        <slimResult>pass(Ordered Query:FIT Presented Hotels)</slimResult>
                <expectation>
                    <status>pass</status>
                    <instructionId>queryTable_1_0</instructionId>
                    <col>0</col>
                              <row>0</row>
                    <type>ConstructionExpectation</type>
                                        <evaluationMessage>Ordered Query:FIT Presented Hotels</evaluationMessage>
                  </expectation>
              </instructionResult>
            <instructionResult>
        <instruction>{id='queryTable_1_2', instruction='call', instanceName='queryTable_1', methodName='query', args=[]}</instruction>
        <slimResult>pass()</slimResult>
                <expectation>
                    <status>pass</status>
                    <instructionId>queryTable_1_2</instructionId>
                              <type>QueryTableExpectation</type>
                                      </expectation>
              </instructionResult>
            <instructionResult>
        <instruction>{id='decisionTable_2_0', instruction='make', instanceName='decisionTable_2', className='FITHotelDataSet', args=[fakeData3]}</instruction>
        <slimResult>pass(FIT Hotel Data Set)</slimResult>
                <expectation>
                    <status>pass</status>
                    <instructionId>decisionTable_2_0</instructionId>
                    <col>0</col>
                              <row>0</row>
                    <type>ConstructionExpectation</type>
                                        <evaluationMessage>FIT Hotel Data Set</evaluationMessage>
                  </expectation>
              </instructionResult>
            <instructionResult>
        <instruction>{id='decisionTable_2_4', instruction='call', instanceName='decisionTable_2', methodName='setTitle', args=[hotel1]}</instruction>
        <slimResult></slimResult>
                <expectation>
                    <instructionId>decisionTable_2_4</instructionId>
                    <col>0</col>
                              <row>2</row>
                    <type>VoidReturnExpectation</type>
                                      </expectation>
              </instructionResult>
            <instructionResult>
        <instruction>{id='decisionTable_2_5', instruction='call', instanceName='decisionTable_2', methodName='setStarRating', args=[1]}</instruction>
        <slimResult></slimResult>
                <expectation>
                    <instructionId>decisionTable_2_5</instructionId>
                    <col>1</col>
                              <row>2</row>
                    <type>VoidReturnExpectation</type>
                                      </expectation>
              </instructionResult>
            <instructionResult>
        <instruction>{id='decisionTable_2_6', instruction='call', instanceName='decisionTable_2', methodName='setImageUrl', args=[http://hotel1.com]}</instruction>
        <slimResult></slimResult>
                <expectation>
                    <instructionId>decisionTable_2_6</instructionId>
                    <col>2</col>
                              <row>2</row>
                    <type>VoidReturnExpectation</type>
                                      </expectation>
              </instructionResult>
            <instructionResult>
        <instruction>{id='decisionTable_2_7', instruction='call', instanceName='decisionTable_2', methodName='setId', args=[1]}</instruction>
        <slimResult></slimResult>
                <expectation>
                    <instructionId>decisionTable_2_7</instructionId>
                    <col>3</col>
                              <row>2</row>
                    <type>VoidReturnExpectation</type>
                                      </expectation>
              </instructionResult>
            <instructionResult>
        <instruction>{id='decisionTable_2_10', instruction='call', instanceName='decisionTable_2', methodName='setTitle', args=[hotel2]}</instruction>
        <slimResult></slimResult>
                <expectation>
                    <instructionId>decisionTable_2_10</instructionId>
                    <col>0</col>
                              <row>3</row>
                    <type>VoidReturnExpectation</type>
                                      </expectation>
              </instructionResult>
            <instructionResult>
        <instruction>{id='decisionTable_2_11', instruction='call', instanceName='decisionTable_2', methodName='setStarRating', args=[2.5]}</instruction>
        <slimResult></slimResult>
                <expectation>
                    <instructionId>decisionTable_2_11</instructionId>
                    <col>1</col>
                              <row>3</row>
                    <type>VoidReturnExpectation</type>
                                      </expectation>
              </instructionResult>
            <instructionResult>
        <instruction>{id='decisionTable_2_12', instruction='call', instanceName='decisionTable_2', methodName='setImageUrl', args=[http://hotel2.com]}</instruction>
        <slimResult></slimResult>
                <expectation>
                    <instructionId>decisionTable_2_12</instructionId>
                    <col>2</col>
                              <row>3</row>
                    <type>VoidReturnExpectation</type>
                                      </expectation>
              </instructionResult>
            <instructionResult>
        <instruction>{id='decisionTable_2_13', instruction='call', instanceName='decisionTable_2', methodName='setId', args=[]}</instruction>
        <slimResult></slimResult>
                <expectation>
                    <instructionId>decisionTable_2_13</instructionId>
                    <col>3</col>
                              <row>3</row>
                    <type>VoidReturnExpectation</type>
                                      </expectation>
              </instructionResult>
            <instructionResult>
        <instruction>{id='decisionTable_2_16', instruction='call', instanceName='decisionTable_2', methodName='setTitle', args=[hotel3]}</instruction>
        <slimResult></slimResult>
                <expectation>
                    <instructionId>decisionTable_2_16</instructionId>
                    <col>0</col>
                              <row>4</row>
                    <type>VoidReturnExpectation</type>
                                      </expectation>
              </instructionResult>
            <instructionResult>
        <instruction>{id='decisionTable_2_17', instruction='call', instanceName='decisionTable_2', methodName='setStarRating', args=[5]}</instruction>
        <slimResult></slimResult>
                <expectation>
                    <instructionId>decisionTable_2_17</instructionId>
                    <col>1</col>
                              <row>4</row>
                    <type>VoidReturnExpectation</type>
                                      </expectation>
              </instructionResult>
            <instructionResult>
        <instruction>{id='decisionTable_2_18', instruction='call', instanceName='decisionTable_2', methodName='setImageUrl', args=[http://hotel3.com]}</instruction>
        <slimResult></slimResult>
                <expectation>
                    <instructionId>decisionTable_2_18</instructionId>
                    <col>2</col>
                              <row>4</row>
                    <type>VoidReturnExpectation</type>
                                      </expectation>
              </instructionResult>
            <instructionResult>
        <instruction>{id='decisionTable_2_19', instruction='call', instanceName='decisionTable_2', methodName='setId', args=[3]}</instruction>
        <slimResult></slimResult>
                <expectation>
                    <instructionId>decisionTable_2_19</instructionId>
                    <col>3</col>
                              <row>4</row>
                    <type>VoidReturnExpectation</type>
                                      </expectation>
              </instructionResult>
            <instructionResult>
        <instruction>{id='queryTable_3_0', instruction='make', instanceName='queryTable_3', className='FITPresentedHotels', args=[fakeData3]}</instruction>
        <slimResult>pass(Ordered Query:FIT Presented Hotels)</slimResult>
                <expectation>
                    <status>pass</status>
                    <instructionId>queryTable_3_0</instructionId>
                    <col>0</col>
                              <row>0</row>
                    <type>ConstructionExpectation</type>
                                        <evaluationMessage>Ordered Query:FIT Presented Hotels</evaluationMessage>
                  </expectation>
              </instructionResult>
            <instructionResult>
        <instruction>{id='queryTable_3_2', instruction='call', instanceName='queryTable_3', methodName='query', args=[]}</instruction>
        <slimResult>pass()</slimResult>
                <expectation>
                    <status>pass</status>
                    <instructionId>queryTable_3_2</instructionId>
                              <type>QueryTableExpectation</type>
                                      </expectation>
              </instructionResult>
            <instructionResult>
        <instruction>{id='decisionTable_4_0', instruction='make', instanceName='decisionTable_4', className='FITPresentedError', args=[]}</instruction>
        <slimResult></slimResult>
                <expectation>
                    <status>error</status>
                    <instructionId>decisionTable_4_0</instructionId>
                              <type>ConstructionExpectation</type>
                                        <evaluationMessage>Could not find class FITPresentedError.</evaluationMessage>
                  </expectation>
              </instructionResult>
            <instructionResult>
        <instruction>{id='decisionTable_4_1', instruction='call', instanceName='decisionTable_4', methodName='table', args=[[[error, http status, displayed text?], [no error, , ], [http error, 400, Network error please try again], [time out, , Time out please try again], [data invalid, , Data invalid please try again]]]}</instruction>
        <slimResult></slimResult>
                <expectation>
                    <status>error</status>
                    <instructionId>decisionTable_4_1</instructionId>
                              <type>SilentReturnExpectation</type>
                                        <evaluationMessage>The instance decisionTable_4. does not exist</evaluationMessage>
                  </expectation>
              </instructionResult>
            <instructionResult>
        <instruction>{id='decisionTable_4_2', instruction='call', instanceName='decisionTable_4', methodName='beginTable', args=[]}</instruction>
        <slimResult></slimResult>
                <expectation>
                    <status>error</status>
                    <instructionId>decisionTable_4_2</instructionId>
                              <type>SilentReturnExpectation</type>
                                        <evaluationMessage>The instance decisionTable_4. does not exist</evaluationMessage>
                  </expectation>
              </instructionResult>
            <instructionResult>
        <instruction>{id='decisionTable_4_3', instruction='call', instanceName='decisionTable_4', methodName='reset', args=[]}</instruction>
        <slimResult></slimResult>
                <expectation>
                    <status>error</status>
                    <instructionId>decisionTable_4_3</instructionId>
                              <type>SilentReturnExpectation</type>
                                        <evaluationMessage>The instance decisionTable_4. does not exist</evaluationMessage>
                  </expectation>
              </instructionResult>
            <instructionResult>
        <instruction>{id='decisionTable_4_4', instruction='call', instanceName='decisionTable_4', methodName='setError', args=[no error]}</instruction>
        <slimResult></slimResult>
                <expectation>
                    <status>error</status>
                    <instructionId>decisionTable_4_4</instructionId>
                              <type>VoidReturnExpectation</type>
                                        <evaluationMessage>The instance decisionTable_4. does not exist</evaluationMessage>
                  </expectation>
              </instructionResult>
            <instructionResult>
        <instruction>{id='decisionTable_4_5', instruction='call', instanceName='decisionTable_4', methodName='setHttpStatus', args=[]}</instruction>
        <slimResult></slimResult>
                <expectation>
                    <status>error</status>
                    <instructionId>decisionTable_4_5</instructionId>
                              <type>VoidReturnExpectation</type>
                                        <evaluationMessage>The instance decisionTable_4. does not exist</evaluationMessage>
                  </expectation>
              </instructionResult>
            <instructionResult>
        <instruction>{id='decisionTable_4_6', instruction='call', instanceName='decisionTable_4', methodName='execute', args=[]}</instruction>
        <slimResult></slimResult>
                <expectation>
                    <status>error</status>
                    <instructionId>decisionTable_4_6</instructionId>
                              <type>SilentReturnExpectation</type>
                                        <evaluationMessage>The instance decisionTable_4. does not exist</evaluationMessage>
                  </expectation>
              </instructionResult>
            <instructionResult>
        <instruction>{id='decisionTable_4_7', instruction='call', instanceName='decisionTable_4', methodName='displayedText', args=[]}</instruction>
        <slimResult></slimResult>
                <expectation>
                    <status>error</status>
                    <instructionId>decisionTable_4_7</instructionId>
                              <type>ReturnedValueExpectation</type>
                                        <evaluationMessage>The instance decisionTable_4. does not exist</evaluationMessage>
                  </expectation>
              </instructionResult>
            <instructionResult>
        <instruction>{id='decisionTable_4_8', instruction='call', instanceName='decisionTable_4', methodName='reset', args=[]}</instruction>
        <slimResult></slimResult>
                <expectation>
                    <status>error</status>
                    <instructionId>decisionTable_4_8</instructionId>
                              <type>SilentReturnExpectation</type>
                                        <evaluationMessage>The instance decisionTable_4. does not exist</evaluationMessage>
                  </expectation>
              </instructionResult>
            <instructionResult>
        <instruction>{id='decisionTable_4_9', instruction='call', instanceName='decisionTable_4', methodName='setError', args=[http error]}</instruction>
        <slimResult></slimResult>
                <expectation>
                    <status>error</status>
                    <instructionId>decisionTable_4_9</instructionId>
                              <type>VoidReturnExpectation</type>
                                        <evaluationMessage>The instance decisionTable_4. does not exist</evaluationMessage>
                  </expectation>
              </instructionResult>
            <instructionResult>
        <instruction>{id='decisionTable_4_10', instruction='call', instanceName='decisionTable_4', methodName='setHttpStatus', args=[400]}</instruction>
        <slimResult></slimResult>
                <expectation>
                    <status>error</status>
                    <instructionId>decisionTable_4_10</instructionId>
                              <type>VoidReturnExpectation</type>
                                        <evaluationMessage>The instance decisionTable_4. does not exist</evaluationMessage>
                  </expectation>
              </instructionResult>
            <instructionResult>
        <instruction>{id='decisionTable_4_11', instruction='call', instanceName='decisionTable_4', methodName='execute', args=[]}</instruction>
        <slimResult></slimResult>
                <expectation>
                    <status>error</status>
                    <instructionId>decisionTable_4_11</instructionId>
                              <type>SilentReturnExpectation</type>
                                        <evaluationMessage>The instance decisionTable_4. does not exist</evaluationMessage>
                  </expectation>
              </instructionResult>
            <instructionResult>
        <instruction>{id='decisionTable_4_12', instruction='call', instanceName='decisionTable_4', methodName='displayedText', args=[]}</instruction>
        <slimResult></slimResult>
                <expectation>
                    <status>error</status>
                    <instructionId>decisionTable_4_12</instructionId>
                              <type>ReturnedValueExpectation</type>
                                        <evaluationMessage>The instance decisionTable_4. does not exist</evaluationMessage>
                  </expectation>
              </instructionResult>
            <instructionResult>
        <instruction>{id='decisionTable_4_13', instruction='call', instanceName='decisionTable_4', methodName='reset', args=[]}</instruction>
        <slimResult></slimResult>
                <expectation>
                    <status>error</status>
                    <instructionId>decisionTable_4_13</instructionId>
                              <type>SilentReturnExpectation</type>
                                        <evaluationMessage>The instance decisionTable_4. does not exist</evaluationMessage>
                  </expectation>
              </instructionResult>
            <instructionResult>
        <instruction>{id='decisionTable_4_14', instruction='call', instanceName='decisionTable_4', methodName='setError', args=[time out]}</instruction>
        <slimResult></slimResult>
                <expectation>
                    <status>error</status>
                    <instructionId>decisionTable_4_14</instructionId>
                              <type>VoidReturnExpectation</type>
                                        <evaluationMessage>The instance decisionTable_4. does not exist</evaluationMessage>
                  </expectation>
              </instructionResult>
            <instructionResult>
        <instruction>{id='decisionTable_4_15', instruction='call', instanceName='decisionTable_4', methodName='setHttpStatus', args=[]}</instruction>
        <slimResult></slimResult>
                <expectation>
                    <status>error</status>
                    <instructionId>decisionTable_4_15</instructionId>
                              <type>VoidReturnExpectation</type>
                                        <evaluationMessage>The instance decisionTable_4. does not exist</evaluationMessage>
                  </expectation>
              </instructionResult>
            <instructionResult>
        <instruction>{id='decisionTable_4_16', instruction='call', instanceName='decisionTable_4', methodName='execute', args=[]}</instruction>
        <slimResult></slimResult>
                <expectation>
                    <status>error</status>
                    <instructionId>decisionTable_4_16</instructionId>
                              <type>SilentReturnExpectation</type>
                                        <evaluationMessage>The instance decisionTable_4. does not exist</evaluationMessage>
                  </expectation>
              </instructionResult>
            <instructionResult>
        <instruction>{id='decisionTable_4_17', instruction='call', instanceName='decisionTable_4', methodName='displayedText', args=[]}</instruction>
        <slimResult></slimResult>
                <expectation>
                    <status>error</status>
                    <instructionId>decisionTable_4_17</instructionId>
                              <type>ReturnedValueExpectation</type>
                                        <evaluationMessage>The instance decisionTable_4. does not exist</evaluationMessage>
                  </expectation>
              </instructionResult>
            <instructionResult>
        <instruction>{id='decisionTable_4_18', instruction='call', instanceName='decisionTable_4', methodName='reset', args=[]}</instruction>
        <slimResult></slimResult>
                <expectation>
                    <status>error</status>
                    <instructionId>decisionTable_4_18</instructionId>
                              <type>SilentReturnExpectation</type>
                                        <evaluationMessage>The instance decisionTable_4. does not exist</evaluationMessage>
                  </expectation>
              </instructionResult>
            <instructionResult>
        <instruction>{id='decisionTable_4_19', instruction='call', instanceName='decisionTable_4', methodName='setError', args=[data invalid]}</instruction>
        <slimResult></slimResult>
                <expectation>
                    <status>error</status>
                    <instructionId>decisionTable_4_19</instructionId>
                              <type>VoidReturnExpectation</type>
                                        <evaluationMessage>The instance decisionTable_4. does not exist</evaluationMessage>
                  </expectation>
              </instructionResult>
            <instructionResult>
        <instruction>{id='decisionTable_4_20', instruction='call', instanceName='decisionTable_4', methodName='setHttpStatus', args=[]}</instruction>
        <slimResult></slimResult>
                <expectation>
                    <status>error</status>
                    <instructionId>decisionTable_4_20</instructionId>
                              <type>VoidReturnExpectation</type>
                                        <evaluationMessage>The instance decisionTable_4. does not exist</evaluationMessage>
                  </expectation>
              </instructionResult>
            <instructionResult>
        <instruction>{id='decisionTable_4_21', instruction='call', instanceName='decisionTable_4', methodName='execute', args=[]}</instruction>
        <slimResult></slimResult>
                <expectation>
                    <status>error</status>
                    <instructionId>decisionTable_4_21</instructionId>
                              <type>SilentReturnExpectation</type>
                                        <evaluationMessage>The instance decisionTable_4. does not exist</evaluationMessage>
                  </expectation>
              </instructionResult>
            <instructionResult>
        <instruction>{id='decisionTable_4_22', instruction='call', instanceName='decisionTable_4', methodName='displayedText', args=[]}</instruction>
        <slimResult></slimResult>
                <expectation>
                    <status>error</status>
                    <instructionId>decisionTable_4_22</instructionId>
                              <type>ReturnedValueExpectation</type>
                                        <evaluationMessage>The instance decisionTable_4. does not exist</evaluationMessage>
                  </expectation>
              </instructionResult>
            <instructionResult>
        <instruction>{id='decisionTable_4_23', instruction='call', instanceName='decisionTable_4', methodName='endTable', args=[]}</instruction>
        <slimResult></slimResult>
                <expectation>
                    <status>error</status>
                    <instructionId>decisionTable_4_23</instructionId>
                              <type>SilentReturnExpectation</type>
                                        <evaluationMessage>The instance decisionTable_4. does not exist</evaluationMessage>
                  </expectation>
              </instructionResult>
            <instructionResult>
        <instruction>{id='scriptTable_5_0', instruction='make', instanceName='scriptTableActor', className='PresentedDetails', args=[]}</instruction>
        <slimResult></slimResult>
                <expectation>
                    <status>error</status>
                    <instructionId>scriptTable_5_0</instructionId>
                              <type>ConstructionExpectation</type>
                                        <evaluationMessage>Could not find class PresentedDetails.</evaluationMessage>
                  </expectation>
              </instructionResult>
            <instructionResult>
        <instruction>{id='scriptTable_5_1', instruction='call', instanceName='scriptTableActor', methodName='selectRowShowingDetails', args=[1, hotel 2]}</instruction>
        <slimResult></slimResult>
                <expectation>
                    <status>error</status>
                    <instructionId>scriptTable_5_1</instructionId>
                              <type>ScriptActionExpectation</type>
                                        <evaluationMessage>The instance scriptTableActor. does not exist</evaluationMessage>
                  </expectation>
              </instructionResult>
          </instructions>
      </result>
  <executionLog>
    <testSystem>slim:./OCSlimProjectTestRunner.sh</testSystem>
    <command>./OCSlimProjectTestRunner.sh 8087</command>
    <exitCode>0</exitCode>
    <stdOut>Running Test Target "AcceptanceTests.app" with Slim Port "8087"
Simulator Device "iPhone-6", deployment Target "9.3"
</stdOut>
    <stdErr>App Spec: &lt;DTiPhoneSimulatorApplicationSpecifier 0x7fcba1f40fe0&gt; specified by app path /Users/richardmoult/Library/Developer/Xcode/DerivedData/ListOfHotels-drlkryelzyywsofihnyoapzwlqvv/Build/Products/Debug-iphonesimulator/AcceptanceTests.app
SDK Root: &lt;DTiPhoneSimulatorSystemRoot 0x7fcba1e84240&gt; path=/Applications/Xcode.app/Contents/Developer/Platforms/WatchSimulator.platform/Developer/SDKs/WatchSimulator.sdk
Creating named pipe at `/var/folders/rd/vg6gwglx159_70t4w5n0n85r0000gn/T//ios-sim-stderr-pipe-1461234327'
Creating named pipe at `/var/folders/rd/vg6gwglx159_70t4w5n0n85r0000gn/T//ios-sim-stdout-pipe-1461234327'
using device family iphone
2016-04-21 11:25:27.600 ios-sim[1716:108723] [MT] DVTAssertions: Warning in /Library/Caches/com.apple.xbs/Sources/DVTFrameworks/DVTFrameworks-10174/DVTFoundation/PlugInArchitecture/PlugInManager/DVTPlugInManager.m:260
Details:  Requested but did not find extension point with identifier Xcode.DVTFoundation.DevicePlatformMapping
Object:   &lt;DVTPlugInManager: 0x7fcba4009cf0&gt;
Method:   -extensionPointWithIdentifier:
Thread:   &lt;NSThread: 0x7fcba1c0bd50&gt;{number = 1, name = main}
Please file a bug at http://bugreport.apple.com with this warning message and any useful information you can provide.
Session started
Session did end with error (null)
Removing named pipe at `/var/folders/rd/vg6gwglx159_70t4w5n0n85r0000gn/T//ios-sim-stderr-pipe-1461234327'
Removing named pipe at `/var/folders/rd/vg6gwglx159_70t4w5n0n85r0000gn/T//ios-sim-stdout-pipe-1461234327'
</stdErr>
  </executionLog>
  <finalCounts>
    <right>0</right>
    <wrong>1</wrong>
    <ignores>0</ignores>
    <exceptions>0</exceptions>
  </finalCounts>
  <totalRunTimeInMillis>3472</totalRunTimeInMillis>
</testResults>

